LICENSE
MANIFEST.in
README.md
requirements.txt
setup.cfg
setup.py
normflows/__init__.py
normflows/core.py
normflows/transforms.py
normflows.egg-info/PKG-INFO
normflows.egg-info/SOURCES.txt
normflows.egg-info/dependency_links.txt
normflows.egg-info/requires.txt
normflows.egg-info/top_level.txt
normflows/distributions/__init__.py
normflows/distributions/base.py
normflows/distributions/decoder.py
normflows/distributions/encoder.py
normflows/distributions/linear_interpolation.py
normflows/distributions/mh_proposal.py
normflows/distributions/prior.py
normflows/distributions/target.py
normflows/flows/__init__.py
normflows/flows/base.py
normflows/flows/flow_test.py
normflows/flows/mixing.py
normflows/flows/normalization.py
normflows/flows/periodic.py
normflows/flows/planar.py
normflows/flows/planar_test.py
normflows/flows/radial.py
normflows/flows/radial_test.py
normflows/flows/reshape.py
normflows/flows/residual.py
normflows/flows/residual_test.py
normflows/flows/stochastic.py
normflows/flows/affine/__init__.py
normflows/flows/affine/autoregressive.py
normflows/flows/affine/autoregressive_test.py
normflows/flows/affine/coupling.py
normflows/flows/affine/coupling_test.py
normflows/flows/affine/glow.py
normflows/flows/affine/glow_test.py
normflows/flows/neural_spline/__init__.py
normflows/flows/neural_spline/autoregressive.py
normflows/flows/neural_spline/autoregressive_test.py
normflows/flows/neural_spline/coupling.py
normflows/flows/neural_spline/coupling_test.py
normflows/flows/neural_spline/wrapper.py
normflows/flows/neural_spline/wrapper_test.py
normflows/nets/__init__.py
normflows/nets/cnn.py
normflows/nets/lipschitz.py
normflows/nets/made.py
normflows/nets/made_test.py
normflows/nets/mlp.py
normflows/nets/resnet.py
normflows/sampling/__init__.py
normflows/sampling/hais.py
normflows/utils/__init__.py
normflows/utils/eval.py
normflows/utils/masks.py
normflows/utils/nn.py
normflows/utils/optim.py
normflows/utils/preprocessing.py
normflows/utils/splines.py
normflows/utils/splines_test.py