Metadata-Version: 2.1
Name: normflows
Version: 1.5
Summary: Pytorch implementation of normalizing flows
Home-page: https://github.com/VincentStimper/normalizing-flows
Author: Vincent Stimper
Author-email: vincent.stimper@tuebingen.mpg.de
License: MIT
Download-URL: https://github.com/VincentStimper/normalizing-flows/archive/refs/heads/master.zip
Platform: UNKNOWN
Classifier: Development Status :: 3 - Alpha
Classifier: Intended Audience :: Developers
Classifier: Programming Language :: Python :: 3
Provides-Extra: docs
License-File: LICENSE
